AUTHORS
CHANGELOG.txt
DESCRIPTION
LICENSE
MANIFEST.in
README.md
requirements.txt
setup.cfg
setup.py
django_hijack_admin.egg-info/PKG-INFO
django_hijack_admin.egg-info/SOURCES.txt
django_hijack_admin.egg-info/dependency_links.txt
django_hijack_admin.egg-info/requires.txt
django_hijack_admin.egg-info/top_level.txt
hijack_admin/__init__.py
hijack_admin/admin.py
hijack_admin/apps.py
hijack_admin/checks.py
hijack_admin/models.py
hijack_admin/settings.py
hijack_admin/views.py
hijack_admin/locale/de/LC_MESSAGES/django.mo
hijack_admin/locale/de/LC_MESSAGES/django.po
hijack_admin/locale/en/LC_MESSAGES/django.mo
hijack_admin/locale/en/LC_MESSAGES/django.po
hijack_admin/locale/fr/LC_MESSAGES/django.mo
hijack_admin/locale/fr/LC_MESSAGES/django.po
hijack_admin/locale/ru/LC_MESSAGES/django.mo
hijack_admin/locale/ru/LC_MESSAGES/django.po
hijack_admin/templates/hijack_admin/admin_button.html
hijack_admin/tests/__init__.py
hijack_admin/tests/manage_settings.py
hijack_admin/tests/south_settings.py
hijack_admin/tests/test_checks.py
hijack_admin/tests/test_hijack_admin.py
hijack_admin/tests/test_settings.py
hijack_admin/tests/urls.py
hijack_admin/tests/test_app/__init__.py
hijack_admin/tests/test_app/authorization_checks.py
hijack_admin/tests/test_app/decorators.py
hijack_admin/tests/test_app/models.py
hijack_admin/tests/test_app/urls.py
hijack_admin/tests/test_app/views.py
hijack_admin/tests/test_app/templates/404.html
hijack_admin/tests/test_app/templates/hello.html
hijack_admin/tests/test_app/templates/hello_filter.html