Metadata-Version: 1.1
Name: django-hijack-admin
Version: 2.1.6
Summary: Django admin integration for Django Hijack (https://github.com/arteria/django-hijack/)
